[
  {
    "name": "sleep",
    "minutes": 0,
    "daysPerWeek": 7,
    "category": "sleep",
    "hours": 7
  },
  {
    "name": "eat breakfast",
    "minutes": 45,
    "daysPerWeek": 7,
    "category": "food",
    "hours": 0
  },
  {
    "name": "Rudy AM walk",
    "minutes": 30,
    "daysPerWeek": 7,
    "category": "pet",
    "hours": 0
  },
  {
    "name": "eat lunch",
    "minutes": 30,
    "daysPerWeek": 7,
    "category": "food",
    "hours": 0
  },
  {
    "name": "Rudy lunch walk",
    "minutes": 0,
    "daysPerWeek": 7,
    "category": "pet",
    "hours": 1
  },
  {
    "name": "cook/eat dinner",
    "minutes": 15,
    "daysPerWeek": 7,
    "category": "food",
    "hours": 1
  },
  {
    "name": "Rudy PM walk",
    "minutes": 30,
    "daysPerWeek": 7,
    "category": "pet",
    "hours": 0
  },
  {
    "name": "exercise",
    "minutes": 45,
    "daysPerWeek": 5,
    "category": "health",
    "hours": 0
  },
  {
    "name": "study math",
    "minutes": 0,
    "daysPerWeek": 4,
    "category": "study",
    "hours": 1
  },
  {
    "name": "read novel",
    "minutes": 45,
    "daysPerWeek": 7,
    "category": "leisure",
    "hours": 0
  },
  {
    "name": "birdwatching",
    "minutes": 30,
    "daysPerWeek": 1,
    "category": "leisure",
    "hours": 2
  },
  {
    "name": "grocery shopping",
    "minutes": 30,
    "daysPerWeek": 1,
    "category": "chores",
    "hours": 1
  },
  {
    "name": "vacuum",
    "minutes": 45,
    "daysPerWeek": 1,
    "category": "chores",
    "hours": 0
  },
  {
    "name": "watch a movie",
    "minutes": 0,
    "daysPerWeek": 1,
    "category": "leisure",
    "hours": 2
  },
  {
    "name": "go on a hike",
    "minutes": 0,
    "daysPerWeek": 1,
    "category": "health",
    "hours": 3
  },
  {
    "name": "work",
    "minutes": 0,
    "daysPerWeek": 5,
    "category": "work",
    "hours": 10
  }
]